[
  {
    "title": "Animal_L6",
    "link_thumb": "https://live.staticflickr.com/65535/51695509495_2948110344_o.gif",
    "id_album": "-1172738451",
    "total": 21,
    "size_max_detail_page": 1,
    "list_detail": [
      {
        "index_page": 0,
        "link_page": "https://github.com/lmbstudiocontact/mb5_dt_alb_0/raw/main/14132021_dta_-1172738451_index_0.json"
      }
    ]
  },
  {
    "title": "Birds_L7",
    "link_thumb": "https://live.staticflickr.com/65535/51695484344_63c540a08e_o.gif",
    "id_album": "1119566096",
    "total": 2,
    "size_max_detail_page": 1,
    "list_detail": [
      {
        "index_page": 0,
        "link_page": "https://github.com/lmbstudiocontact/mb5_dt_alb_0/raw/main/14132021_dta_1119566096_index_0.json"
      }
    ]
  },
  {
    "title": "Sheep_L6",
    "link_thumb": "https://live.staticflickr.com/65535/51703612911_553804ae10_o.gif",
    "id_album": "-576277778",
    "total": 2,
    "size_max_detail_page": 1,
    "list_detail": [
      {
        "index_page": 0,
        "link_page": "https://github.com/lmbstudiocontact/mb5_dt_alb_0/raw/main/14132021_dta_-576277778_index_0.json"
      }
    ]
  },
  {
    "title": "Onmyoji_L1",
    "link_thumb": "https://live.staticflickr.com/65535/51701099832_c74e62344c_o.gif",
    "id_album": "389318913",
    "total": 26,
    "size_max_detail_page": 1,
    "list_detail": [
      {
        "index_page": 0,
        "link_page": "https://github.com/lmbstudiocontact/mb5_dt_alb_0/raw/main/14132021_dta_389318913_index_0.json"
      }
    ]
  },
  {
    "title": "Star War_L4",
    "link_thumb": "https://live.staticflickr.com/65535/51704532014_0487eb0d1b_o.gif",
    "id_album": "-1637191763",
    "total": 2,
    "size_max_detail_page": 1,
    "list_detail": [
      {
        "index_page": 0,
        "link_page": "https://github.com/lmbstudiocontact/mb5_dt_alb_0/raw/main/14132021_dta_-1637191763_index_0.json"
      }
    ]
  },
  {
    "title": "Star War_L2",
    "link_thumb": "https://live.staticflickr.com/65535/51704527229_7bd419fa8a_o.gif",
    "id_album": "-1637191765",
    "total": 2,
    "size_max_detail_page": 1,
    "list_detail": [
      {
        "index_page": 0,
        "link_page": "https://github.com/lmbstudiocontact/mb5_dt_alb_0/raw/main/14132021_dta_-1637191765_index_0.json"
      }
    ]
  },
  {
    "title": "Angry Birds_L4",
    "link_thumb": "https://live.staticflickr.com/65535/51695403910_ab3cb6301a_o.gif",
    "id_album": "2112729292",
    "total": 26,
    "size_max_detail_page": 1,
    "list_detail": [
      {
        "index_page": 0,
        "link_page": "https://github.com/lmbstudiocontact/mb5_dt_alb_0/raw/main/14132021_dta_2112729292_index_0.json"
      }
    ]
  },
  {
    "title": "Kung Fu Panda_L5",
    "link_thumb": "https://live.staticflickr.com/65535/51698753252_e3196e45bf_o.gif",
    "id_album": "1222783554",
    "total": 2,
    "size_max_detail_page": 1,
    "list_detail": [
      {
        "index_page": 0,
        "link_page": "https://github.com/lmbstudiocontact/mb5_dt_alb_0/raw/main/14132021_dta_1222783554_index_0.json"
      }
    ]
  },
  {
    "title": "Shiv_L3",
    "link_thumb": "https://live.staticflickr.com/65535/51702851037_d615a55a17_o.gif",
    "id_album": "-568595356",
    "total": 32,
    "size_max_detail_page": 1,
    "list_detail": [
      {
        "index_page": 0,
        "link_page": "https://github.com/lmbstudiocontact/mb5_dt_alb_0/raw/main/14132021_dta_-568595356_index_0.json"
      }
    ]
  }
]