[
  {
    "title": "Rio 2_L3",
    "link_thumb": "https://live.staticflickr.com/65535/51787538603_4bf5b1cb6a_o.gif",
    "id_album": "-1210862916",
    "total": 17,
    "size_max_detail_page": 1,
    "list_detail": [
      {
        "index_page": 0,
        "link_page": "https://github.com/lmbstudiocontact/mb5_dt_alb_0/raw/main/14132021_dta_-1210862916_index_0.json"
      }
    ]
  },
  {
    "title": "Doraemon Anime_L3",
    "link_thumb": "https://live.staticflickr.com/65535/51787821134_c7156cb91d_o.gif",
    "id_album": "405661393",
    "total": 16,
    "size_max_detail_page": 1,
    "list_detail": [
      {
        "index_page": 0,
        "link_page": "https://github.com/lmbstudiocontact/mb5_dt_alb_0/raw/main/14132021_dta_405661393_index_0.json"
      }
    ]
  },
  {
    "title": "Panda Art_L1",
    "link_thumb": "https://live.staticflickr.com/65535/51788155110_205f390b8e_o.gif",
    "id_album": "586574343",
    "total": 5,
    "size_max_detail_page": 1,
    "list_detail": [
      {
        "index_page": 0,
        "link_page": "https://github.com/lmbstudiocontact/mb5_dt_alb_0/raw/main/14132021_dta_586574343_index_0.json"
      }
    ]
  },
  {
    "title": "Mickey Cartoon_L4",
    "link_thumb": "https://live.staticflickr.com/65535/51788120090_665ac5b1ae_o.gif",
    "id_album": "1680949825",
    "total": 22,
    "size_max_detail_page": 1,
    "list_detail": [
      {
        "index_page": 0,
        "link_page": "https://github.com/lmbstudiocontact/mb5_dt_alb_0/raw/main/14132021_dta_1680949825_index_0.json"
      }
    ]
  },
  {
    "title": "Boss Baby Cartoon_L5",
    "link_thumb": "https://live.staticflickr.com/65535/51787218111_84c02d2114_o.gif",
    "id_album": "158762705",
    "total": 16,
    "size_max_detail_page": 1,
    "list_detail": [
      {
        "index_page": 0,
        "link_page": "https://github.com/lmbstudiocontact/mb5_dt_alb_0/raw/main/14132021_dta_158762705_index_0.json"
      }
    ]
  },
  {
    "title": "Plants Vs Zombies_L5",
    "link_thumb": "https://live.staticflickr.com/65535/51788156410_5d79a371a0_o.gif",
    "id_album": "-1426777466",
    "total": 24,
    "size_max_detail_page": 1,
    "list_detail": [
      {
        "index_page": 0,
        "link_page": "https://github.com/lmbstudiocontact/mb5_dt_alb_0/raw/main/14132021_dta_-1426777466_index_0.json"
      }
    ]
  },
  {
    "title": "Shiv_L1",
    "link_thumb": "https://live.staticflickr.com/65535/51787272136_c56901b356_o.gif",
    "id_album": "-568595358",
    "total": 32,
    "size_max_detail_page": 1,
    "list_detail": [
      {
        "index_page": 0,
        "link_page": "https://github.com/lmbstudiocontact/mb5_dt_alb_0/raw/main/14132021_dta_-568595358_index_0.json"
      }
    ]
  },
  {
    "title": "Kitty & My Melody_L4",
    "link_thumb": "https://live.staticflickr.com/65535/51786424097_cb0acfda48_o.gif",
    "id_album": "-378480542",
    "total": 76,
    "size_max_detail_page": 2,
    "list_detail": [
      {
        "index_page": 0,
        "link_page": "https://github.com/lmbstudiocontact/mb5_dt_alb_0/raw/main/14132021_dta_-378480542_index_0.json"
      },
      {
        "index_page": 1,
        "link_page": "https://github.com/lmbstudiocontact/mb5_dt_alb_0/raw/main/14132021_dta_-378480542_index_1.json"
      }
    ]
  },
  {
    "title": "Doraemon Anime_L1",
    "link_thumb": "https://live.staticflickr.com/65535/51787202521_42373a3b86_o.gif",
    "id_album": "405661391",
    "total": 16,
    "size_max_detail_page": 1,
    "list_detail": [
      {
        "index_page": 0,
        "link_page": "https://github.com/lmbstudiocontact/mb5_dt_alb_0/raw/main/14132021_dta_405661391_index_0.json"
      }
    ]
  },
  {
    "title": "Football_L5",
    "link_thumb": "https://live.staticflickr.com/65535/51788112395_4d31f7420d_o.gif",
    "id_album": "-371026085",
    "total": 49,
    "size_max_detail_page": 1,
    "list_detail": [
      {
        "index_page": 0,
        "link_page": "https://github.com/lmbstudiocontact/mb5_dt_alb_0/raw/main/14132021_dta_-371026085_index_0.json"
      }
    ]
  },
  {
    "title": "Fox Art_L3",
    "link_thumb": "https://live.staticflickr.com/65535/51788105205_af8d63b569_o.gif",
    "id_album": "-646110860",
    "total": 7,
    "size_max_detail_page": 1,
    "list_detail": [
      {
        "index_page": 0,
        "link_page": "https://github.com/lmbstudiocontact/mb5_dt_alb_0/raw/main/14132021_dta_-646110860_index_0.json"
      }
    ]
  },
  {
    "title": "Rio 2_L1",
    "link_thumb": "https://live.staticflickr.com/65535/51787918524_20f9c25f4b_o.gif",
    "id_album": "-1210862918",
    "total": 17,
    "size_max_detail_page": 1,
    "list_detail": [
      {
        "index_page": 0,
        "link_page": "https://github.com/lmbstudiocontact/mb5_dt_alb_0/raw/main/14132021_dta_-1210862918_index_0.json"
      }
    ]
  },
  {
    "title": "Kung Fu Panda_L2",
    "link_thumb": "https://live.staticflickr.com/65535/51786446742_b270b46918_o.gif",
    "id_album": "1222783551",
    "total": 2,
    "size_max_detail_page": 1,
    "list_detail": [
      {
        "index_page": 0,
        "link_page": "https://github.com/lmbstudiocontact/mb5_dt_alb_0/raw/main/14132021_dta_1222783551_index_0.json"
      }
    ]
  },
  {
    "title": "Sheep_L7",
    "link_thumb": "https://live.staticflickr.com/65535/51787273771_ac4f0401a3_o.gif",
    "id_album": "-576277777",
    "total": 2,
    "size_max_detail_page": 1,
    "list_detail": [
      {
        "index_page": 0,
        "link_page": "https://github.com/lmbstudiocontact/mb5_dt_alb_0/raw/main/14132021_dta_-576277777_index_0.json"
      }
    ]
  },
  {
    "title": "One Punch Man Anime_L5",
    "link_thumb": "https://live.staticflickr.com/65535/51787535998_e9e66e22cd_o.gif",
    "id_album": "-1626855610",
    "total": 2,
    "size_max_detail_page": 1,
    "list_detail": [
      {
        "index_page": 0,
        "link_page": "https://github.com/lmbstudiocontact/mb5_dt_alb_0/raw/main/14132021_dta_-1626855610_index_0.json"
      }
    ]
  },
  {
    "title": "Milkmokka Fofo_L7",
    "link_thumb": "https://live.staticflickr.com/65535/51787237681_ffc3e05c7f_o.gif",
    "id_album": "-1232313348",
    "total": 32,
    "size_max_detail_page": 1,
    "list_detail": [
      {
        "index_page": 0,
        "link_page": "https://github.com/lmbstudiocontact/mb5_dt_alb_0/raw/main/14132021_dta_-1232313348_index_0.json"
      }
    ]
  },
  {
    "title": "Moana Cartoon_L2",
    "link_thumb": "https://live.staticflickr.com/65535/51787918024_2c35aa11c0_o.gif",
    "id_album": "-2101867515",
    "total": 13,
    "size_max_detail_page": 1,
    "list_detail": [
      {
        "index_page": 0,
        "link_page": "https://github.com/lmbstudiocontact/mb5_dt_alb_0/raw/main/14132021_dta_-2101867515_index_0.json"
      }
    ]
  },
  {
    "title": "Dragon Art_L3",
    "link_thumb": "https://live.staticflickr.com/65535/51788091280_50856969e4_o.gif",
    "id_album": "2059014000",
    "total": 13,
    "size_max_detail_page": 1,
    "list_detail": [
      {
        "index_page": 0,
        "link_page": "https://github.com/lmbstudiocontact/mb5_dt_alb_0/raw/main/14132021_dta_2059014000_index_0.json"
      }
    ]
  },
  {
    "title": "Scenery",
    "link_thumb": "https://live.staticflickr.com/65535/51787475908_178eb21fe4_o.gif",
    "id_album": "-715666509",
    "total": 2,
    "size_max_detail_page": 1,
    "list_detail": [
      {
        "index_page": 0,
        "link_page": "https://github.com/lmbstudiocontact/mb5_dt_alb_0/raw/main/14132021_dta_-715666509_index_0.json"
      }
    ]
  },
  {
    "title": "Milkmokka Fofo_L6",
    "link_thumb": "https://live.staticflickr.com/65535/51788114205_0fb966a82d_o.gif",
    "id_album": "-1232313349",
    "total": 29,
    "size_max_detail_page": 1,
    "list_detail": [
      {
        "index_page": 0,
        "link_page": "https://github.com/lmbstudiocontact/mb5_dt_alb_0/raw/main/14132021_dta_-1232313349_index_0.json"
      }
    ]
  },
  {
    "title": "Moana Cartoon_L1",
    "link_thumb": "https://live.staticflickr.com/65535/51788167145_abe0fe3066_o.gif",
    "id_album": "-2101867516",
    "total": 13,
    "size_max_detail_page": 1,
    "list_detail": [
      {
        "index_page": 0,
        "link_page": "https://github.com/lmbstudiocontact/mb5_dt_alb_0/raw/main/14132021_dta_-2101867516_index_0.json"
      }
    ]
  },
  {
    "title": "Poke_L6",
    "link_thumb": "https://live.staticflickr.com/65535/51787519293_ee59326d87_o.gif",
    "id_album": "1265605552",
    "total": 32,
    "size_max_detail_page": 1,
    "list_detail": [
      {
        "index_page": 0,
        "link_page": "https://github.com/lmbstudiocontact/mb5_dt_alb_0/raw/main/14132021_dta_1265605552_index_0.json"
      }
    ]
  },
  {
    "title": "Simpsons Cartoon_L5",
    "link_thumb": "https://live.staticflickr.com/65535/51788147395_de1a7cc0f6_o.gif",
    "id_album": "1276946592",
    "total": 8,
    "size_max_detail_page": 1,
    "list_detail": [
      {
        "index_page": 0,
        "link_page": "https://github.com/lmbstudiocontact/mb5_dt_alb_0/raw/main/14132021_dta_1276946592_index_0.json"
      }
    ]
  },
  {
    "title": "Couple Art_L6",
    "link_thumb": "https://live.staticflickr.com/65535/51787441133_a80cdb64af_o.gif",
    "id_album": "1239230758",
    "total": 37,
    "size_max_detail_page": 1,
    "list_detail": [
      {
        "index_page": 0,
        "link_page": "https://github.com/lmbstudiocontact/mb5_dt_alb_0/raw/main/14132021_dta_1239230758_index_0.json"
      }
    ]
  },
  {
    "title": "Shiv_L4",
    "link_thumb": "https://live.staticflickr.com/65535/51787250146_86d6e86fdd_o.gif",
    "id_album": "-568595355",
    "total": 32,
    "size_max_detail_page": 1,
    "list_detail": [
      {
        "index_page": 0,
        "link_page": "https://github.com/lmbstudiocontact/mb5_dt_alb_0/raw/main/14132021_dta_-568595355_index_0.json"
      }
    ]
  },
  {
    "title": "Donald Duck Cartoon_L1",
    "link_thumb": "https://live.staticflickr.com/65535/51787206001_823073a1e8_o.gif",
    "id_album": "-1917621485",
    "total": 4,
    "size_max_detail_page": 1,
    "list_detail": [
      {
        "index_page": 0,
        "link_page": "https://github.com/lmbstudiocontact/mb5_dt_alb_0/raw/main/14132021_dta_-1917621485_index_0.json"
      }
    ]
  },
  {
    "title": "Pokmon Anime_L5",
    "link_thumb": "https://live.staticflickr.com/65535/51787517038_4b2f8c2831_o.gif",
    "id_album": "-555824140",
    "total": 108,
    "size_max_detail_page": 3,
    "list_detail": [
      {
        "index_page": 0,
        "link_page": "https://github.com/lmbstudiocontact/mb5_dt_alb_0/raw/main/14132021_dta_-555824140_index_0.json"
      },
      {
        "index_page": 1,
        "link_page": "https://github.com/lmbstudiocontact/mb5_dt_alb_0/raw/main/14132021_dta_-555824140_index_1.json"
      },
      {
        "index_page": 2,
        "link_page": "https://github.com/lmbstudiocontact/mb5_dt_alb_0/raw/main/14132021_dta_-555824140_index_2.json"
      }
    ]
  },
  {
    "title": "Horror Art_L4",
    "link_thumb": "https://live.staticflickr.com/65535/51788108605_4ac3e73826_o.gif",
    "id_album": "529377274",
    "total": 41,
    "size_max_detail_page": 1,
    "list_detail": [
      {
        "index_page": 0,
        "link_page": "https://github.com/lmbstudiocontact/mb5_dt_alb_0/raw/main/14132021_dta_529377274_index_0.json"
      }
    ]
  },
  {
    "title": "Pokmon Anime_L4",
    "link_thumb": "https://live.staticflickr.com/65535/51787274136_81c776c07a_o.gif",
    "id_album": "-555824141",
    "total": 108,
    "size_max_detail_page": 3,
    "list_detail": [
      {
        "index_page": 0,
        "link_page": "https://github.com/lmbstudiocontact/mb5_dt_alb_0/raw/main/14132021_dta_-555824141_index_0.json"
      },
      {
        "index_page": 1,
        "link_page": "https://github.com/lmbstudiocontact/mb5_dt_alb_0/raw/main/14132021_dta_-555824141_index_1.json"
      },
      {
        "index_page": 2,
        "link_page": "https://github.com/lmbstudiocontact/mb5_dt_alb_0/raw/main/14132021_dta_-555824141_index_2.json"
      }
    ]
  },
  {
    "title": "Buddhist Terms_L1",
    "link_thumb": "https://live.staticflickr.com/65535/51787203691_b0f95a86f8_o.gif",
    "id_album": "518853928",
    "total": 13,
    "size_max_detail_page": 1,
    "list_detail": [
      {
        "index_page": 0,
        "link_page": "https://github.com/lmbstudiocontact/mb5_dt_alb_0/raw/main/14132021_dta_518853928_index_0.json"
      }
    ]
  },
  {
    "title": "Madagascar Cartoon_L4",
    "link_thumb": "https://live.staticflickr.com/65535/51787524528_356944a653_o.gif",
    "id_album": "-2014542387",
    "total": 9,
    "size_max_detail_page": 1,
    "list_detail": [
      {
        "index_page": 0,
        "link_page": "https://github.com/lmbstudiocontact/mb5_dt_alb_0/raw/main/14132021_dta_-2014542387_index_0.json"
      }
    ]
  },
  {
    "title": "Lilo & Stitch Cartoon_L5",
    "link_thumb": "https://live.staticflickr.com/65535/51788124995_8483e757f6_o.gif",
    "id_album": "685543663",
    "total": 30,
    "size_max_detail_page": 1,
    "list_detail": [
      {
        "index_page": 0,
        "link_page": "https://github.com/lmbstudiocontact/mb5_dt_alb_0/raw/main/14132021_dta_685543663_index_0.json"
      }
    ]
  },
  {
    "title": "Disney Cartoon_L1",
    "link_thumb": "https://live.staticflickr.com/65535/51787466358_4da8a2e620_o.gif",
    "id_album": "-779586270",
    "total": 54,
    "size_max_detail_page": 2,
    "list_detail": [
      {
        "index_page": 0,
        "link_page": "https://github.com/lmbstudiocontact/mb5_dt_alb_0/raw/main/14132021_dta_-779586270_index_0.json"
      },
      {
        "index_page": 1,
        "link_page": "https://github.com/lmbstudiocontact/mb5_dt_alb_0/raw/main/14132021_dta_-779586270_index_1.json"
      }
    ]
  },
  {
    "title": "Fox Art_L4",
    "link_thumb": "https://live.staticflickr.com/65535/51787482753_1d827173e2_o.gif",
    "id_album": "-646110859",
    "total": 7,
    "size_max_detail_page": 1,
    "list_detail": [
      {
        "index_page": 0,
        "link_page": "https://github.com/lmbstudiocontact/mb5_dt_alb_0/raw/main/14132021_dta_-646110859_index_0.json"
      }
    ]
  },
  {
    "title": "Kung Fu Panda_L1",
    "link_thumb": "https://live.staticflickr.com/65535/51786446867_7beaf41a34_o.gif",
    "id_album": "1222783550",
    "total": 2,
    "size_max_detail_page": 1,
    "list_detail": [
      {
        "index_page": 0,
        "link_page": "https://github.com/lmbstudiocontact/mb5_dt_alb_0/raw/main/14132021_dta_1222783550_index_0.json"
      }
    ]
  },
  {
    "title": "Cute Art_L4",
    "link_thumb": "https://live.staticflickr.com/65535/51787836584_80c2e78efa_o.gif",
    "id_album": "-629963487",
    "total": 76,
    "size_max_detail_page": 2,
    "list_detail": [
      {
        "index_page": 0,
        "link_page": "https://github.com/lmbstudiocontact/mb5_dt_alb_0/raw/main/14132021_dta_-629963487_index_0.json"
      },
      {
        "index_page": 1,
        "link_page": "https://github.com/lmbstudiocontact/mb5_dt_alb_0/raw/main/14132021_dta_-629963487_index_1.json"
      }
    ]
  },
  {
    "title": "Wolf_L2",
    "link_thumb": "https://live.staticflickr.com/65535/51787877699_fb2570fcc6_o.gif",
    "id_album": "-1110849965",
    "total": 5,
    "size_max_detail_page": 1,
    "list_detail": [
      {
        "index_page": 0,
        "link_page": "https://github.com/lmbstudiocontact/mb5_dt_alb_0/raw/main/14132021_dta_-1110849965_index_0.json"
      }
    ]
  },
  {
    "title": "Horror Art_L3",
    "link_thumb": "https://live.staticflickr.com/65535/51787495718_f7ff184cc5_o.gif",
    "id_album": "529377273",
    "total": 41,
    "size_max_detail_page": 1,
    "list_detail": [
      {
        "index_page": 0,
        "link_page": "https://github.com/lmbstudiocontact/mb5_dt_alb_0/raw/main/14132021_dta_529377273_index_0.json"
      }
    ]
  },
  {
    "title": "Couple_L2",
    "link_thumb": "https://live.staticflickr.com/65535/51787204891_25b56e5382_o.gif",
    "id_album": "-888889819",
    "total": 24,
    "size_max_detail_page": 1,
    "list_detail": [
      {
        "index_page": 0,
        "link_page": "https://github.com/lmbstudiocontact/mb5_dt_alb_0/raw/main/14132021_dta_-888889819_index_0.json"
      }
    ]
  },
  {
    "title": "Star War_L4",
    "link_thumb": "https://live.staticflickr.com/65535/51787500363_fb6a427697_o.gif",
    "id_album": "-1637191763",
    "total": 2,
    "size_max_detail_page": 1,
    "list_detail": [
      {
        "index_page": 0,
        "link_page": "https://github.com/lmbstudiocontact/mb5_dt_alb_0/raw/main/14132021_dta_-1637191763_index_0.json"
      }
    ]
  },
  {
    "title": "Unicorn_L7",
    "link_thumb": "https://live.staticflickr.com/65535/51787255646_2c31df5f55_o.gif",
    "id_album": "-1508743534",
    "total": 20,
    "size_max_detail_page": 1,
    "list_detail": [
      {
        "index_page": 0,
        "link_page": "https://github.com/lmbstudiocontact/mb5_dt_alb_0/raw/main/14132021_dta_-1508743534_index_0.json"
      }
    ]
  },
  {
    "title": "Buddhist Terms_L4",
    "link_thumb": "https://live.staticflickr.com/65535/51788069390_5a87b96dca_o.gif",
    "id_album": "518853931",
    "total": 13,
    "size_max_detail_page": 1,
    "list_detail": [
      {
        "index_page": 0,
        "link_page": "https://github.com/lmbstudiocontact/mb5_dt_alb_0/raw/main/14132021_dta_518853931_index_0.json"
      }
    ]
  },
  {
    "title": "Music_L3",
    "link_thumb": "https://live.staticflickr.com/65535/51786446707_cde68e3849_o.gif",
    "id_album": "908522977",
    "total": 24,
    "size_max_detail_page": 1,
    "list_detail": [
      {
        "index_page": 0,
        "link_page": "https://github.com/lmbstudiocontact/mb5_dt_alb_0/raw/main/14132021_dta_908522977_index_0.json"
      }
    ]
  },
  {
    "title": "Wolf_L3",
    "link_thumb": "https://live.staticflickr.com/65535/51787503098_2b9fd6a79b_o.gif",
    "id_album": "-1110849964",
    "total": 5,
    "size_max_detail_page": 1,
    "list_detail": [
      {
        "index_page": 0,
        "link_page": "https://github.com/lmbstudiocontact/mb5_dt_alb_0/raw/main/14132021_dta_-1110849964_index_0.json"
      }
    ]
  },
  {
    "title": "Pokmon Anime_L2",
    "link_thumb": "https://live.staticflickr.com/65535/51786474052_5d7a0e45d6_o.gif",
    "id_album": "-555824143",
    "total": 108,
    "size_max_detail_page": 3,
    "list_detail": [
      {
        "index_page": 0,
        "link_page": "https://github.com/lmbstudiocontact/mb5_dt_alb_0/raw/main/14132021_dta_-555824143_index_0.json"
      },
      {
        "index_page": 1,
        "link_page": "https://github.com/lmbstudiocontact/mb5_dt_alb_0/raw/main/14132021_dta_-555824143_index_1.json"
      },
      {
        "index_page": 2,
        "link_page": "https://github.com/lmbstudiocontact/mb5_dt_alb_0/raw/main/14132021_dta_-555824143_index_2.json"
      }
    ]
  },
  {
    "title": "Dog_L6",
    "link_thumb": "https://live.staticflickr.com/65535/51787208491_0465ab33ba_o.gif",
    "id_album": "2052455277",
    "total": 22,
    "size_max_detail_page": 1,
    "list_detail": [
      {
        "index_page": 0,
        "link_page": "https://github.com/lmbstudiocontact/mb5_dt_alb_0/raw/main/14132021_dta_2052455277_index_0.json"
      }
    ]
  },
  {
    "title": "Joker Harley Quinn_L5",
    "link_thumb": "https://live.staticflickr.com/65535/51788117095_b429e0ac99_o.gif",
    "id_album": "-2022175633",
    "total": 24,
    "size_max_detail_page": 1,
    "list_detail": [
      {
        "index_page": 0,
        "link_page": "https://github.com/lmbstudiocontact/mb5_dt_alb_0/raw/main/14132021_dta_-2022175633_index_0.json"
      }
    ]
  },
  {
    "title": "Joker Harley Quinn_L4",
    "link_thumb": "https://live.staticflickr.com/65535/51787878864_f19265a6c4_o.gif",
    "id_album": "-2022175634",
    "total": 24,
    "size_max_detail_page": 1,
    "list_detail": [
      {
        "index_page": 0,
        "link_page": "https://github.com/lmbstudiocontact/mb5_dt_alb_0/raw/main/14132021_dta_-2022175634_index_0.json"
      }
    ]
  },
  {
    "title": "Lilo & Stitch Cartoon_L2",
    "link_thumb": "https://live.staticflickr.com/65535/51787276636_162d342301_o.gif",
    "id_album": "685543660",
    "total": 30,
    "size_max_detail_page": 1,
    "list_detail": [
      {
        "index_page": 0,
        "link_page": "https://github.com/lmbstudiocontact/mb5_dt_alb_0/raw/main/14132021_dta_685543660_index_0.json"
      }
    ]
  },
  {
    "title": "Donald Duck Cartoon_L3",
    "link_thumb": "https://live.staticflickr.com/65535/51788076395_97df286d89_o.gif",
    "id_album": "-1917621483",
    "total": 4,
    "size_max_detail_page": 1,
    "list_detail": [
      {
        "index_page": 0,
        "link_page": "https://github.com/lmbstudiocontact/mb5_dt_alb_0/raw/main/14132021_dta_-1917621483_index_0.json"
      }
    ]
  }
]