[
  {
    "title": "Kitty & My Melody_L2",
    "link_thumb": "https://live.staticflickr.com/65535/51780881034_98d2a36c39_o.gif",
    "id_album": "-378480544",
    "total": 76,
    "size_max_detail_page": 2,
    "list_detail": [
      {
        "index_page": 0,
        "link_page": "https://github.com/lmbstudiocontact/mb5_dt_alb_0/raw/main/14132021_dta_-378480544_index_0.json"
      },
      {
        "index_page": 1,
        "link_page": "https://github.com/lmbstudiocontact/mb5_dt_alb_0/raw/main/14132021_dta_-378480544_index_1.json"
      }
    ]
  },
  {
    "title": "Anime Chibi_L6",
    "link_thumb": "https://live.staticflickr.com/65535/51780791664_7a635e1575_o.gif",
    "id_album": "-1298448214",
    "total": 12,
    "size_max_detail_page": 1,
    "list_detail": [
      {
        "index_page": 0,
        "link_page": "https://github.com/lmbstudiocontact/mb5_dt_alb_0/raw/main/14132021_dta_-1298448214_index_0.json"
      }
    ]
  },
  {
    "title": "Rio 2_L2",
    "link_thumb": "https://live.staticflickr.com/65535/51780276246_dd839d6ce7_n.jpg",
    "id_album": "-1210862917",
    "total": 17,
    "size_max_detail_page": 1,
    "list_detail": [
      {
        "index_page": 0,
        "link_page": "https://github.com/lmbstudiocontact/mb5_dt_alb_0/raw/main/14132021_dta_-1210862917_index_0.json"
      }
    ]
  },
  {
    "title": "Buddhist Terms_L1",
    "link_thumb": "https://live.staticflickr.com/65535/51781039440_5f50a5a3f6_o.gif",
    "id_album": "518853928",
    "total": 13,
    "size_max_detail_page": 1,
    "list_detail": [
      {
        "index_page": 0,
        "link_page": "https://github.com/lmbstudiocontact/mb5_dt_alb_0/raw/main/14132021_dta_518853928_index_0.json"
      }
    ]
  },
  {
    "title": "Birds_L6",
    "link_thumb": "https://live.staticflickr.com/65535/51694011512_2a5cf1581f_o.gif",
    "id_album": "1119566095",
    "total": 1,
    "size_max_detail_page": 1,
    "list_detail": [
      {
        "index_page": 0,
        "link_page": "https://github.com/lmbstudiocontact/mb5_dt_alb_0/raw/main/14132021_dta_1119566095_index_0.json"
      }
    ]
  },
  {
    "title": "Boss Baby Cartoon_L2",
    "link_thumb": "https://live.staticflickr.com/65535/51780171396_c142ff3289_o.gif",
    "id_album": "158762702",
    "total": 16,
    "size_max_detail_page": 1,
    "list_detail": [
      {
        "index_page": 0,
        "link_page": "https://github.com/lmbstudiocontact/mb5_dt_alb_0/raw/main/14132021_dta_158762702_index_0.json"
      }
    ]
  },
  {
    "title": "Doraemon Anime_L2",
    "link_thumb": "https://live.staticflickr.com/65535/51780187381_ee13b5ed0d_o.gif",
    "id_album": "405661392",
    "total": 16,
    "size_max_detail_page": 1,
    "list_detail": [
      {
        "index_page": 0,
        "link_page": "https://github.com/lmbstudiocontact/mb5_dt_alb_0/raw/main/14132021_dta_405661392_index_0.json"
      }
    ]
  },
  {
    "title": "Detective Conan_L4",
    "link_thumb": "https://live.staticflickr.com/65535/51780794729_80d937c6b8_o.gif",
    "id_album": "-1285383389",
    "total": 16,
    "size_max_detail_page": 1,
    "list_detail": [
      {
        "index_page": 0,
        "link_page": "https://github.com/lmbstudiocontact/mb5_dt_alb_0/raw/main/14132021_dta_-1285383389_index_0.json"
      }
    ]
  },
  {
    "title": "One Punch Man Anime_L2",
    "link_thumb": "https://live.staticflickr.com/65535/51780546888_aef2150ef2_o.gif",
    "id_album": "-1626855613",
    "total": 2,
    "size_max_detail_page": 1,
    "list_detail": [
      {
        "index_page": 0,
        "link_page": "https://github.com/lmbstudiocontact/mb5_dt_alb_0/raw/main/14132021_dta_-1626855613_index_0.json"
      }
    ]
  },
  {
    "title": "Music_L2",
    "link_thumb": "https://live.staticflickr.com/65535/51700013852_53be79ceab_o.gif",
    "id_album": "908522976",
    "total": 24,
    "size_max_detail_page": 1,
    "list_detail": [
      {
        "index_page": 0,
        "link_page": "https://github.com/lmbstudiocontact/mb5_dt_alb_0/raw/main/14132021_dta_908522976_index_0.json"
      }
    ]
  },
  {
    "title": "One Piece Anime_L4",
    "link_thumb": "https://live.staticflickr.com/65535/51780242106_baf17a7d34_o.gif",
    "id_album": "1351456607",
    "total": 135,
    "size_max_detail_page": 3,
    "list_detail": [
      {
        "index_page": 0,
        "link_page": "https://github.com/lmbstudiocontact/mb5_dt_alb_0/raw/main/14132021_dta_1351456607_index_0.json"
      },
      {
        "index_page": 1,
        "link_page": "https://github.com/lmbstudiocontact/mb5_dt_alb_0/raw/main/14132021_dta_1351456607_index_1.json"
      },
      {
        "index_page": 2,
        "link_page": "https://github.com/lmbstudiocontact/mb5_dt_alb_0/raw/main/14132021_dta_1351456607_index_2.json"
      }
    ]
  },
  {
    "title": "Mickey Cartoon_L2",
    "link_thumb": "https://live.staticflickr.com/65535/51780854049_8254228b38_o.gif",
    "id_album": "1680949823",
    "total": 22,
    "size_max_detail_page": 1,
    "list_detail": [
      {
        "index_page": 0,
        "link_page": "https://github.com/lmbstudiocontact/mb5_dt_alb_0/raw/main/14132021_dta_1680949823_index_0.json"
      }
    ]
  },
  {
    "title": "Moana Cartoon_L1",
    "link_thumb": "https://live.staticflickr.com/65535/51780246661_e889c35097_o.gif",
    "id_album": "-2101867516",
    "total": 13,
    "size_max_detail_page": 1,
    "list_detail": [
      {
        "index_page": 0,
        "link_page": "https://github.com/lmbstudiocontact/mb5_dt_alb_0/raw/main/14132021_dta_-2101867516_index_0.json"
      }
    ]
  },
  {
    "title": "Mickey Cartoon_L1",
    "link_thumb": "https://live.staticflickr.com/65535/51780859609_dc6c61abe2_o.gif",
    "id_album": "1680949822",
    "total": 22,
    "size_max_detail_page": 1,
    "list_detail": [
      {
        "index_page": 0,
        "link_page": "https://github.com/lmbstudiocontact/mb5_dt_alb_0/raw/main/14132021_dta_1680949822_index_0.json"
      }
    ]
  },
  {
    "title": "Milkmokka Fofo_L7",
    "link_thumb": "https://live.staticflickr.com/65535/51780892614_4da07c2d44_o.gif",
    "id_album": "-1232313348",
    "total": 32,
    "size_max_detail_page": 1,
    "list_detail": [
      {
        "index_page": 0,
        "link_page": "https://github.com/lmbstudiocontact/mb5_dt_alb_0/raw/main/14132021_dta_-1232313348_index_0.json"
      }
    ]
  },
  {
    "title": "Game",
    "link_thumb": "https://live.staticflickr.com/65535/51694973465_6a6a6af034_o.gif",
    "id_album": "2211858",
    "total": 100,
    "size_max_detail_page": 2,
    "list_detail": [
      {
        "index_page": 0,
        "link_page": "https://github.com/lmbstudiocontact/mb5_dt_alb_0/raw/main/14132021_dta_2211858_index_0.json"
      },
      {
        "index_page": 1,
        "link_page": "https://github.com/lmbstudiocontact/mb5_dt_alb_0/raw/main/14132021_dta_2211858_index_1.json"
      }
    ]
  },
  {
    "title": "Dragon Ball Anime_L3",
    "link_thumb": "https://live.staticflickr.com/65535/51780823669_3de416289c_o.gif",
    "id_album": "1464725222",
    "total": 60,
    "size_max_detail_page": 2,
    "list_detail": [
      {
        "index_page": 0,
        "link_page": "https://github.com/lmbstudiocontact/mb5_dt_alb_0/raw/main/14132021_dta_1464725222_index_0.json"
      },
      {
        "index_page": 1,
        "link_page": "https://github.com/lmbstudiocontact/mb5_dt_alb_0/raw/main/14132021_dta_1464725222_index_1.json"
      }
    ]
  },
  {
    "title": "Lilo & Stitch Cartoon_L4",
    "link_thumb": "https://live.staticflickr.com/65535/51780902079_0636becf0f_o.gif",
    "id_album": "685543662",
    "total": 30,
    "size_max_detail_page": 1,
    "list_detail": [
      {
        "index_page": 0,
        "link_page": "https://github.com/lmbstudiocontact/mb5_dt_alb_0/raw/main/14132021_dta_685543662_index_0.json"
      }
    ]
  },
  {
    "title": "My Melody Bunny_L6",
    "link_thumb": "https://live.staticflickr.com/65535/51781102210_079afee344_o.gif",
    "id_album": "1796214687",
    "total": 49,
    "size_max_detail_page": 1,
    "list_detail": [
      {
        "index_page": 0,
        "link_page": "https://github.com/lmbstudiocontact/mb5_dt_alb_0/raw/main/14132021_dta_1796214687_index_0.json"
      }
    ]
  },
  {
    "title": "One Piece Anime_L3",
    "link_thumb": "https://live.staticflickr.com/65535/51780270026_b9d87d778b_o.gif",
    "id_album": "1351456606",
    "total": 135,
    "size_max_detail_page": 3,
    "list_detail": [
      {
        "index_page": 0,
        "link_page": "https://github.com/lmbstudiocontact/mb5_dt_alb_0/raw/main/14132021_dta_1351456606_index_0.json"
      },
      {
        "index_page": 1,
        "link_page": "https://github.com/lmbstudiocontact/mb5_dt_alb_0/raw/main/14132021_dta_1351456606_index_1.json"
      },
      {
        "index_page": 2,
        "link_page": "https://github.com/lmbstudiocontact/mb5_dt_alb_0/raw/main/14132021_dta_1351456606_index_2.json"
      }
    ]
  },
  {
    "title": "Boku No Hero Academia Anime_L2",
    "link_thumb": "https://live.staticflickr.com/65535/51780783194_b18a3dee14_o.gif",
    "id_album": "197312540",
    "total": 19,
    "size_max_detail_page": 1,
    "list_detail": [
      {
        "index_page": 0,
        "link_page": "https://github.com/lmbstudiocontact/mb5_dt_alb_0/raw/main/14132021_dta_197312540_index_0.json"
      }
    ]
  },
  {
    "title": "Mifit Store",
    "link_thumb": "https://live.staticflickr.com/65535/51700056226_61ee9c6bd6_o.gif",
    "id_album": "-583089738",
    "total": 44,
    "size_max_detail_page": 1,
    "list_detail": [
      {
        "index_page": 0,
        "link_page": "https://github.com/lmbstudiocontact/mb5_dt_alb_0/raw/main/14132021_dta_-583089738_index_0.json"
      }
    ]
  },
  {
    "title": "Joker Harley Quinn_L3",
    "link_thumb": "https://live.staticflickr.com/65535/51780852754_fb94caf48c_o.gif",
    "id_album": "-2022175635",
    "total": 24,
    "size_max_detail_page": 1,
    "list_detail": [
      {
        "index_page": 0,
        "link_page": "https://github.com/lmbstudiocontact/mb5_dt_alb_0/raw/main/14132021_dta_-2022175635_index_0.json"
      }
    ]
  },
  {
    "title": "Horror Art_L1",
    "link_thumb": "https://live.staticflickr.com/65535/51780854219_f99603dfdb_o.gif",
    "id_album": "529377271",
    "total": 41,
    "size_max_detail_page": 1,
    "list_detail": [
      {
        "index_page": 0,
        "link_page": "https://github.com/lmbstudiocontact/mb5_dt_alb_0/raw/main/14132021_dta_529377271_index_0.json"
      }
    ]
  },
  {
    "title": "Dragon Ball Anime_L4",
    "link_thumb": "https://live.staticflickr.com/65535/51779357922_b001f8c1e8_o.gif",
    "id_album": "1464725223",
    "total": 60,
    "size_max_detail_page": 2,
    "list_detail": [
      {
        "index_page": 0,
        "link_page": "https://github.com/lmbstudiocontact/mb5_dt_alb_0/raw/main/14132021_dta_1464725223_index_0.json"
      },
      {
        "index_page": 1,
        "link_page": "https://github.com/lmbstudiocontact/mb5_dt_alb_0/raw/main/14132021_dta_1464725223_index_1.json"
      }
    ]
  },
  {
    "title": "Pokmon Anime_L1",
    "link_thumb": "https://live.staticflickr.com/65535/51781181025_a133a43e4e_o.gif",
    "id_album": "-555824144",
    "total": 108,
    "size_max_detail_page": 3,
    "list_detail": [
      {
        "index_page": 0,
        "link_page": "https://github.com/lmbstudiocontact/mb5_dt_alb_0/raw/main/14132021_dta_-555824144_index_0.json"
      },
      {
        "index_page": 1,
        "link_page": "https://github.com/lmbstudiocontact/mb5_dt_alb_0/raw/main/14132021_dta_-555824144_index_1.json"
      },
      {
        "index_page": 2,
        "link_page": "https://github.com/lmbstudiocontact/mb5_dt_alb_0/raw/main/14132021_dta_-555824144_index_2.json"
      }
    ]
  },
  {
    "title": "Plants Vs Zombies_L1",
    "link_thumb": "https://live.staticflickr.com/65535/51779452992_0d26702638_o.gif",
    "id_album": "-1426777470",
    "total": 24,
    "size_max_detail_page": 1,
    "list_detail": [
      {
        "index_page": 0,
        "link_page": "https://github.com/lmbstudiocontact/mb5_dt_alb_0/raw/main/14132021_dta_-1426777470_index_0.json"
      }
    ]
  },
  {
    "title": "Spider Man Cartoon_L2",
    "link_thumb": "https://live.staticflickr.com/65535/51781190760_54db16785f_n.jpg",
    "id_album": "1735002392",
    "total": 16,
    "size_max_detail_page": 1,
    "list_detail": [
      {
        "index_page": 0,
        "link_page": "https://github.com/lmbstudiocontact/mb5_dt_alb_0/raw/main/14132021_dta_1735002392_index_0.json"
      }
    ]
  },
  {
    "title": "Smurf Houses Cartoon_L5",
    "link_thumb": "https://live.staticflickr.com/65535/51780563898_1e63173f6d_n.jpg",
    "id_album": "228264854",
    "total": 4,
    "size_max_detail_page": 1,
    "list_detail": [
      {
        "index_page": 0,
        "link_page": "https://github.com/lmbstudiocontact/mb5_dt_alb_0/raw/main/14132021_dta_228264854_index_0.json"
      }
    ]
  },
  {
    "title": "Ratatouille Cartoon_L1",
    "link_thumb": "https://live.staticflickr.com/65535/51779469942_8ea2dc1563_n.jpg",
    "id_album": "1746345500",
    "total": 5,
    "size_max_detail_page": 1,
    "list_detail": [
      {
        "index_page": 0,
        "link_page": "https://github.com/lmbstudiocontact/mb5_dt_alb_0/raw/main/14132021_dta_1746345500_index_0.json"
      }
    ]
  },
  {
    "title": "Spider Man Cartoon_L1",
    "link_thumb": "https://live.staticflickr.com/65535/51781195325_512628300b_n.jpg",
    "id_album": "1735002391",
    "total": 16,
    "size_max_detail_page": 1,
    "list_detail": [
      {
        "index_page": 0,
        "link_page": "https://github.com/lmbstudiocontact/mb5_dt_alb_0/raw/main/14132021_dta_1735002391_index_0.json"
      }
    ]
  },
  {
    "title": "Lilo & Stitch Cartoon_L3",
    "link_thumb": "https://live.staticflickr.com/65535/51780517168_e7ee48ba8f_o.gif",
    "id_album": "685543661",
    "total": 30,
    "size_max_detail_page": 1,
    "list_detail": [
      {
        "index_page": 0,
        "link_page": "https://github.com/lmbstudiocontact/mb5_dt_alb_0/raw/main/14132021_dta_685543661_index_0.json"
      }
    ]
  },
  {
    "title": "Horror Art_L4",
    "link_thumb": "https://live.staticflickr.com/65535/51779365167_4017d71ebf_o.gif",
    "id_album": "529377274",
    "total": 41,
    "size_max_detail_page": 1,
    "list_detail": [
      {
        "index_page": 0,
        "link_page": "https://github.com/lmbstudiocontact/mb5_dt_alb_0/raw/main/14132021_dta_529377274_index_0.json"
      }
    ]
  },
  {
    "title": "Naruto Anime_L5",
    "link_thumb": "https://live.staticflickr.com/65535/51780542223_ac1ab8108c_o.gif",
    "id_album": "1894397987",
    "total": 37,
    "size_max_detail_page": 1,
    "list_detail": [
      {
        "index_page": 0,
        "link_page": "https://github.com/lmbstudiocontact/mb5_dt_alb_0/raw/main/14132021_dta_1894397987_index_0.json"
      }
    ]
  },
  {
    "title": "Kung Fu Panda_L5",
    "link_thumb": "https://live.staticflickr.com/65535/51780213096_9de94a3b88_o.gif",
    "id_album": "1222783554",
    "total": 2,
    "size_max_detail_page": 1,
    "list_detail": [
      {
        "index_page": 0,
        "link_page": "https://github.com/lmbstudiocontact/mb5_dt_alb_0/raw/main/14132021_dta_1222783554_index_0.json"
      }
    ]
  },
  {
    "title": "Madagascar Cartoon_L1",
    "link_thumb": "https://live.staticflickr.com/65535/51780873669_3c4c2e4909_o.gif",
    "id_album": "-2014542390",
    "total": 9,
    "size_max_detail_page": 1,
    "list_detail": [
      {
        "index_page": 0,
        "link_page": "https://github.com/lmbstudiocontact/mb5_dt_alb_0/raw/main/14132021_dta_-2014542390_index_0.json"
      }
    ]
  },
  {
    "title": "Music_L3",
    "link_thumb": "https://live.staticflickr.com/65535/51701517034_0449cebf68_o.gif",
    "id_album": "908522977",
    "total": 24,
    "size_max_detail_page": 1,
    "list_detail": [
      {
        "index_page": 0,
        "link_page": "https://github.com/lmbstudiocontact/mb5_dt_alb_0/raw/main/14132021_dta_908522977_index_0.json"
      }
    ]
  },
  {
    "title": "Death Note Anime_L4",
    "link_thumb": "https://live.staticflickr.com/65535/51779350467_e4048203f0_o.gif",
    "id_album": "-374116171",
    "total": 8,
    "size_max_detail_page": 1,
    "list_detail": [
      {
        "index_page": 0,
        "link_page": "https://github.com/lmbstudiocontact/mb5_dt_alb_0/raw/main/14132021_dta_-374116171_index_0.json"
      }
    ]
  },
  {
    "title": "Football_L3",
    "link_thumb": "https://live.staticflickr.com/65535/51698103989_6b1521131a_o.gif",
    "id_album": "-371026087",
    "total": 49,
    "size_max_detail_page": 1,
    "list_detail": [
      {
        "index_page": 0,
        "link_page": "https://github.com/lmbstudiocontact/mb5_dt_alb_0/raw/main/14132021_dta_-371026087_index_0.json"
      }
    ]
  },
  {
    "title": "Molang_L6",
    "link_thumb": "https://live.staticflickr.com/65535/51701500050_63bfbf32b0_o.gif",
    "id_album": "-1608694439",
    "total": 95,
    "size_max_detail_page": 2,
    "list_detail": [
      {
        "index_page": 0,
        "link_page": "https://github.com/lmbstudiocontact/mb5_dt_alb_0/raw/main/14132021_dta_-1608694439_index_0.json"
      },
      {
        "index_page": 1,
        "link_page": "https://github.com/lmbstudiocontact/mb5_dt_alb_0/raw/main/14132021_dta_-1608694439_index_1.json"
      }
    ]
  },
  {
    "title": "Couple Art_L6",
    "link_thumb": "https://live.staticflickr.com/65535/51780778049_e7893f63fb_o.gif",
    "id_album": "1239230758",
    "total": 37,
    "size_max_detail_page": 1,
    "list_detail": [
      {
        "index_page": 0,
        "link_page": "https://github.com/lmbstudiocontact/mb5_dt_alb_0/raw/main/14132021_dta_1239230758_index_0.json"
      }
    ]
  },
  {
    "title": "Buddhist Terms_L5",
    "link_thumb": "https://live.staticflickr.com/65535/51779325877_c8951b1415_o.gif",
    "id_album": "518853932",
    "total": 13,
    "size_max_detail_page": 1,
    "list_detail": [
      {
        "index_page": 0,
        "link_page": "https://github.com/lmbstudiocontact/mb5_dt_alb_0/raw/main/14132021_dta_518853932_index_0.json"
      }
    ]
  },
  {
    "title": "Fox Art_L3",
    "link_thumb": "https://live.staticflickr.com/65535/51780450778_5461c2e729_o.gif",
    "id_album": "-646110860",
    "total": 7,
    "size_max_detail_page": 1,
    "list_detail": [
      {
        "index_page": 0,
        "link_page": "https://github.com/lmbstudiocontact/mb5_dt_alb_0/raw/main/14132021_dta_-646110860_index_0.json"
      }
    ]
  },
  {
    "title": "Lilo & Stitch Cartoon_L1",
    "link_thumb": "https://live.staticflickr.com/65535/51779394942_059077a4fd_o.gif",
    "id_album": "685543659",
    "total": 30,
    "size_max_detail_page": 1,
    "list_detail": [
      {
        "index_page": 0,
        "link_page": "https://github.com/lmbstudiocontact/mb5_dt_alb_0/raw/main/14132021_dta_685543659_index_0.json"
      }
    ]
  },
  {
    "title": "Boy_L7",
    "link_thumb": "https://live.staticflickr.com/65535/51695153126_2c53f57564_o.gif",
    "id_album": "1995733214",
    "total": 65,
    "size_max_detail_page": 2,
    "list_detail": [
      {
        "index_page": 0,
        "link_page": "https://github.com/lmbstudiocontact/mb5_dt_alb_0/raw/main/14132021_dta_1995733214_index_0.json"
      },
      {
        "index_page": 1,
        "link_page": "https://github.com/lmbstudiocontact/mb5_dt_alb_0/raw/main/14132021_dta_1995733214_index_1.json"
      }
    ]
  },
  {
    "title": "Shiv_L4",
    "link_thumb": "https://live.staticflickr.com/65535/51703955908_9a5ef7f40a_o.gif",
    "id_album": "-568595355",
    "total": 32,
    "size_max_detail_page": 1,
    "list_detail": [
      {
        "index_page": 0,
        "link_page": "https://github.com/lmbstudiocontact/mb5_dt_alb_0/raw/main/14132021_dta_-568595355_index_0.json"
      }
    ]
  },
  {
    "title": "Totoro_L6",
    "link_thumb": "https://live.staticflickr.com/65535/51703861771_cb3194b5e3_o.gif",
    "id_album": "1833828886",
    "total": 41,
    "size_max_detail_page": 1,
    "list_detail": [
      {
        "index_page": 0,
        "link_page": "https://github.com/lmbstudiocontact/mb5_dt_alb_0/raw/main/14132021_dta_1833828886_index_0.json"
      }
    ]
  },
  {
    "title": "Boy_L6",
    "link_thumb": "https://live.staticflickr.com/65535/51695058981_35019fa60c_o.gif",
    "id_album": "1995733213",
    "total": 47,
    "size_max_detail_page": 1,
    "list_detail": [
      {
        "index_page": 0,
        "link_page": "https://github.com/lmbstudiocontact/mb5_dt_alb_0/raw/main/14132021_dta_1995733213_index_0.json"
      }
    ]
  },
  {
    "title": "Cute Art_L3",
    "link_thumb": "https://live.staticflickr.com/65535/51780395768_f65d5065c5_o.gif",
    "id_album": "-629963488",
    "total": 76,
    "size_max_detail_page": 2,
    "list_detail": [
      {
        "index_page": 0,
        "link_page": "https://github.com/lmbstudiocontact/mb5_dt_alb_0/raw/main/14132021_dta_-629963488_index_0.json"
      },
      {
        "index_page": 1,
        "link_page": "https://github.com/lmbstudiocontact/mb5_dt_alb_0/raw/main/14132021_dta_-629963488_index_1.json"
      }
    ]
  },
  {
    "title": "Star War_L2",
    "link_thumb": "https://live.staticflickr.com/65535/51780290971_f354e7837e_n.jpg",
    "id_album": "-1637191765",
    "total": 2,
    "size_max_detail_page": 1,
    "list_detail": [
      {
        "index_page": 0,
        "link_page": "https://github.com/lmbstudiocontact/mb5_dt_alb_0/raw/main/14132021_dta_-1637191765_index_0.json"
      }
    ]
  }
]