[
  {
    "title": "Sheep_L6",
    "link_thumb": "https://live.staticflickr.com/65535/51788145735_1463f06049_o.gif",
    "id_album": "-576277778",
    "total": 2,
    "size_max_detail_page": 1,
    "list_detail": [
      {
        "index_page": 0,
        "link_page": "https://github.com/lmbstudiocontact/mb5_dt_alb_0/raw/main/14132021_dta_-576277778_index_0.json"
      }
    ]
  },
  {
    "title": "One Piece Anime_L4",
    "link_thumb": "https://live.staticflickr.com/65535/51787869439_b1bd3722b3_o.gif",
    "id_album": "1351456607",
    "total": 135,
    "size_max_detail_page": 3,
    "list_detail": [
      {
        "index_page": 0,
        "link_page": "https://github.com/lmbstudiocontact/mb5_dt_alb_0/raw/main/14132021_dta_1351456607_index_0.json"
      },
      {
        "index_page": 1,
        "link_page": "https://github.com/lmbstudiocontact/mb5_dt_alb_0/raw/main/14132021_dta_1351456607_index_1.json"
      },
      {
        "index_page": 2,
        "link_page": "https://github.com/lmbstudiocontact/mb5_dt_alb_0/raw/main/14132021_dta_1351456607_index_2.json"
      }
    ]
  },
  {
    "title": "Moana Cartoon_L3",
    "link_thumb": "https://live.staticflickr.com/65535/51787539963_b369178d06_o.gif",
    "id_album": "-2101867514",
    "total": 13,
    "size_max_detail_page": 1,
    "list_detail": [
      {
        "index_page": 0,
        "link_page": "https://github.com/lmbstudiocontact/mb5_dt_alb_0/raw/main/14132021_dta_-2101867514_index_0.json"
      }
    ]
  },
  {
    "title": "Dragon Art_L1",
    "link_thumb": "https://live.staticflickr.com/65535/51787845964_05fc1e632b_o.gif",
    "id_album": "2059013998",
    "total": 13,
    "size_max_detail_page": 1,
    "list_detail": [
      {
        "index_page": 0,
        "link_page": "https://github.com/lmbstudiocontact/mb5_dt_alb_0/raw/main/14132021_dta_2059013998_index_0.json"
      }
    ]
  },
  {
    "title": "Plants Vs Zombies_L1",
    "link_thumb": "https://live.staticflickr.com/65535/51788120345_48e3ed30b9_o.gif",
    "id_album": "-1426777470",
    "total": 24,
    "size_max_detail_page": 1,
    "list_detail": [
      {
        "index_page": 0,
        "link_page": "https://github.com/lmbstudiocontact/mb5_dt_alb_0/raw/main/14132021_dta_-1426777470_index_0.json"
      }
    ]
  },
  {
    "title": "Butterfly_L5",
    "link_thumb": "https://live.staticflickr.com/65535/51787440518_9ec8cc4d8a_o.gif",
    "id_album": "657564373",
    "total": 6,
    "size_max_detail_page": 1,
    "list_detail": [
      {
        "index_page": 0,
        "link_page": "https://github.com/lmbstudiocontact/mb5_dt_alb_0/raw/main/14132021_dta_657564373_index_0.json"
      }
    ]
  },
  {
    "title": "Disney Cartoon_L4",
    "link_thumb": "https://live.staticflickr.com/65535/51786377637_f5e5b7e9ea_o.gif",
    "id_album": "-779586267",
    "total": 54,
    "size_max_detail_page": 2,
    "list_detail": [
      {
        "index_page": 0,
        "link_page": "https://github.com/lmbstudiocontact/mb5_dt_alb_0/raw/main/14132021_dta_-779586267_index_0.json"
      },
      {
        "index_page": 1,
        "link_page": "https://github.com/lmbstudiocontact/mb5_dt_alb_0/raw/main/14132021_dta_-779586267_index_1.json"
      }
    ]
  },
  {
    "title": "Boss Baby Cartoon_L4",
    "link_thumb": "https://live.staticflickr.com/65535/51786380217_080a74ba1d_o.gif",
    "id_album": "158762704",
    "total": 16,
    "size_max_detail_page": 1,
    "list_detail": [
      {
        "index_page": 0,
        "link_page": "https://github.com/lmbstudiocontact/mb5_dt_alb_0/raw/main/14132021_dta_158762704_index_0.json"
      }
    ]
  },
  {
    "title": "Miku",
    "link_thumb": "https://live.staticflickr.com/65535/51787473073_3e40375182_o.gif",
    "id_album": "2398246",
    "total": 5,
    "size_max_detail_page": 1,
    "list_detail": [
      {
        "index_page": 0,
        "link_page": "https://github.com/lmbstudiocontact/mb5_dt_alb_0/raw/main/14132021_dta_2398246_index_0.json"
      }
    ]
  }
]