[
  {
    "title": "Spider Man Cartoon_L1",
    "link_thumb": "https://live.staticflickr.com/65535/51786451347_b44524bd2b_o.gif",
    "id_album": "1735002391",
    "total": 16,
    "size_max_detail_page": 1,
    "list_detail": [
      {
        "index_page": 0,
        "link_page": "https://github.com/lmbstudiocontact/mb5_dt_alb_0/raw/main/14132021_dta_1735002391_index_0.json"
      }
    ]
  },
  {
    "title": "Star War_L1",
    "link_thumb": "https://live.staticflickr.com/65535/51787874574_4f0b5c5bd5_o.gif",
    "id_album": "-1637191766",
    "total": 2,
    "size_max_detail_page": 1,
    "list_detail": [
      {
        "index_page": 0,
        "link_page": "https://github.com/lmbstudiocontact/mb5_dt_alb_0/raw/main/14132021_dta_-1637191766_index_0.json"
      }
    ]
  },
  {
    "title": "Kung Fu Panda_L5",
    "link_thumb": "https://live.staticflickr.com/65535/51787262491_625ee443d1_o.gif",
    "id_album": "1222783554",
    "total": 2,
    "size_max_detail_page": 1,
    "list_detail": [
      {
        "index_page": 0,
        "link_page": "https://github.com/lmbstudiocontact/mb5_dt_alb_0/raw/main/14132021_dta_1222783554_index_0.json"
      }
    ]
  },
  {
    "title": "Animal Art_L5",
    "link_thumb": "https://live.staticflickr.com/65535/51788078980_c256664cc7_o.gif",
    "id_album": "97007465",
    "total": 7,
    "size_max_detail_page": 1,
    "list_detail": [
      {
        "index_page": 0,
        "link_page": "https://github.com/lmbstudiocontact/mb5_dt_alb_0/raw/main/14132021_dta_97007465_index_0.json"
      }
    ]
  },
  {
    "title": "Pooh_L6",
    "link_thumb": "https://live.staticflickr.com/65535/51787913814_9ffe3e0e18_o.gif",
    "id_album": "1269389009",
    "total": 9,
    "size_max_detail_page": 1,
    "list_detail": [
      {
        "index_page": 0,
        "link_page": "https://github.com/lmbstudiocontact/mb5_dt_alb_0/raw/main/14132021_dta_1269389009_index_0.json"
      }
    ]
  },
  {
    "title": "Madagascar Cartoon_L3",
    "link_thumb": "https://live.staticflickr.com/65535/51787276266_3eb4f3107c_o.gif",
    "id_album": "-2014542388",
    "total": 9,
    "size_max_detail_page": 1,
    "list_detail": [
      {
        "index_page": 0,
        "link_page": "https://github.com/lmbstudiocontact/mb5_dt_alb_0/raw/main/14132021_dta_-2014542388_index_0.json"
      }
    ]
  },
  {
    "title": "Boku No Hero Academia Anime_L2",
    "link_thumb": "https://live.staticflickr.com/65535/51787465798_b187957467_o.gif",
    "id_album": "197312540",
    "total": 19,
    "size_max_detail_page": 1,
    "list_detail": [
      {
        "index_page": 0,
        "link_page": "https://github.com/lmbstudiocontact/mb5_dt_alb_0/raw/main/14132021_dta_197312540_index_0.json"
      }
    ]
  },
  {
    "title": "Dragon Ball Anime_L5",
    "link_thumb": "https://live.staticflickr.com/65535/51786389927_53ab1f6220_o.gif",
    "id_album": "1464725224",
    "total": 60,
    "size_max_detail_page": 2,
    "list_detail": [
      {
        "index_page": 0,
        "link_page": "https://github.com/lmbstudiocontact/mb5_dt_alb_0/raw/main/14132021_dta_1464725224_index_0.json"
      },
      {
        "index_page": 1,
        "link_page": "https://github.com/lmbstudiocontact/mb5_dt_alb_0/raw/main/14132021_dta_1464725224_index_1.json"
      }
    ]
  },
  {
    "title": "Totoro_L6",
    "link_thumb": "https://live.staticflickr.com/65535/51786461702_176b1d28b2_o.gif",
    "id_album": "1833828886",
    "total": 41,
    "size_max_detail_page": 1,
    "list_detail": [
      {
        "index_page": 0,
        "link_page": "https://github.com/lmbstudiocontact/mb5_dt_alb_0/raw/main/14132021_dta_1833828886_index_0.json"
      }
    ]
  }
]