[
  {
    "title": "Animal Art_L4",
    "link_thumb": "https://live.staticflickr.com/65535/51788080800_46d75e1a69_o.gif",
    "id_album": "97007464",
    "total": 7,
    "size_max_detail_page": 1,
    "list_detail": [
      {
        "index_page": 0,
        "link_page": "https://github.com/lmbstudiocontact/mb5_dt_alb_0/raw/main/14132021_dta_97007464_index_0.json"
      }
    ]
  },
  {
    "title": "Boku No Hero Academia Anime_L3",
    "link_thumb": "https://live.staticflickr.com/65535/51788085825_d970d2701c_o.gif",
    "id_album": "197312541",
    "total": 19,
    "size_max_detail_page": 1,
    "list_detail": [
      {
        "index_page": 0,
        "link_page": "https://github.com/lmbstudiocontact/mb5_dt_alb_0/raw/main/14132021_dta_197312541_index_0.json"
      }
    ]
  },
  {
    "title": "Wolf_L5",
    "link_thumb": "https://live.staticflickr.com/65535/51787501263_05c3bf9a15_o.gif",
    "id_album": "-1110849962",
    "total": 5,
    "size_max_detail_page": 1,
    "list_detail": [
      {
        "index_page": 0,
        "link_page": "https://github.com/lmbstudiocontact/mb5_dt_alb_0/raw/main/14132021_dta_-1110849962_index_0.json"
      }
    ]
  },
  {
    "title": "Ratatouille Cartoon_L1",
    "link_thumb": "https://live.staticflickr.com/65535/51786481167_3e2e8f95e1_o.gif",
    "id_album": "1746345500",
    "total": 5,
    "size_max_detail_page": 1,
    "list_detail": [
      {
        "index_page": 0,
        "link_page": "https://github.com/lmbstudiocontact/mb5_dt_alb_0/raw/main/14132021_dta_1746345500_index_0.json"
      }
    ]
  },
  {
    "title": "Pokmon Anime_L4",
    "link_thumb": "https://live.staticflickr.com/65535/51787274136_81c776c07a_o.gif",
    "id_album": "-555824141",
    "total": 108,
    "size_max_detail_page": 3,
    "list_detail": [
      {
        "index_page": 0,
        "link_page": "https://github.com/lmbstudiocontact/mb5_dt_alb_0/raw/main/14132021_dta_-555824141_index_0.json"
      },
      {
        "index_page": 1,
        "link_page": "https://github.com/lmbstudiocontact/mb5_dt_alb_0/raw/main/14132021_dta_-555824141_index_1.json"
      },
      {
        "index_page": 2,
        "link_page": "https://github.com/lmbstudiocontact/mb5_dt_alb_0/raw/main/14132021_dta_-555824141_index_2.json"
      }
    ]
  },
  {
    "title": "Donald Duck Cartoon_L1",
    "link_thumb": "https://live.staticflickr.com/65535/51787206001_823073a1e8_o.gif",
    "id_album": "-1917621485",
    "total": 4,
    "size_max_detail_page": 1,
    "list_detail": [
      {
        "index_page": 0,
        "link_page": "https://github.com/lmbstudiocontact/mb5_dt_alb_0/raw/main/14132021_dta_-1917621485_index_0.json"
      }
    ]
  },
  {
    "title": "Joker Harley Quinn_L1",
    "link_thumb": "https://live.staticflickr.com/65535/51787522743_25332da740_o.gif",
    "id_album": "-2022175637",
    "total": 24,
    "size_max_detail_page": 1,
    "list_detail": [
      {
        "index_page": 0,
        "link_page": "https://github.com/lmbstudiocontact/mb5_dt_alb_0/raw/main/14132021_dta_-2022175637_index_0.json"
      }
    ]
  },
  {
    "title": "Tiger_L7",
    "link_thumb": "https://live.staticflickr.com/65535/51787536163_6b76da330c_o.gif",
    "id_album": "2111354123",
    "total": 2,
    "size_max_detail_page": 1,
    "list_detail": [
      {
        "index_page": 0,
        "link_page": "https://github.com/lmbstudiocontact/mb5_dt_alb_0/raw/main/14132021_dta_2111354123_index_0.json"
      }
    ]
  },
  {
    "title": "Animals",
    "link_thumb": "https://live.staticflickr.com/65535/51786407187_fc31c37d84_o.gif",
    "id_album": "807717335",
    "total": 1,
    "size_max_detail_page": 1,
    "list_detail": [
      {
        "index_page": 0,
        "link_page": "https://github.com/lmbstudiocontact/mb5_dt_alb_0/raw/main/14132021_dta_807717335_index_0.json"
      }
    ]
  }
]